odoo10_addon_l10n_it_riba_commission-10.0.1.0.1-py2.7-nspkg.pth
odoo/addons/l10n_it_riba_commission/README.rst
odoo/addons/l10n_it_riba_commission/__init__.py
odoo/addons/l10n_it_riba_commission/__manifest__.py
odoo/addons/l10n_it_riba_commission/i18n/it.po
odoo/addons/l10n_it_riba_commission/models/__init__.py
odoo/addons/l10n_it_riba_commission/models/sale_commission.py
odoo/addons/l10n_it_riba_commission/tests/__init__.py
odoo/addons/l10n_it_riba_commission/tests/test_riba.py
odoo/addons/l10n_it_riba_commission/views/sale_commission.xml
odoo/addons/l10n_it_riba_commission/wizards/__init__.py
odoo/addons/l10n_it_riba_commission/wizards/make_settle.py
odoo10_addon_l10n_it_riba_commission-10.0.1.0.1.dist-info/DESCRIPTION.rst
odoo10_addon_l10n_it_riba_commission-10.0.1.0.1.dist-info/METADATA
odoo10_addon_l10n_it_riba_commission-10.0.1.0.1.dist-info/RECORD
odoo10_addon_l10n_it_riba_commission-10.0.1.0.1.dist-info/WHEEL
odoo10_addon_l10n_it_riba_commission-10.0.1.0.1.dist-info/metadata.json
odoo10_addon_l10n_it_riba_commission-10.0.1.0.1.dist-info/namespace_packages.txt
odoo10_addon_l10n_it_riba_commission-10.0.1.0.1.dist-info/top_level.txt
