Metadata-Version: 2.0
Name: odoo10-addon-l10n-it-riba-commission
Version: 10.0.1.0.1
Summary: Ricevute bancarie & commissioni
Home-page: https://github.com/OCA/l10n-italy/tree/10.0/l10n_it_riba_commission
Author: Agile Business Group, Odoo Community Association (OCA)
Author-email: support@odoo-community.org
License: AGPL-3
Platform: UNKNOWN
Classifier: Programming Language :: Python
Classifier: Framework :: Odoo
Classifier: License :: OSI Approved :: GNU Affero General Public License v3
Requires-Python: ~=2.7
Requires-Dist: odoo (<10.1dev,>=10.0)
Requires-Dist: odoo10-addon-l10n-it-ricevute-bancarie
Requires-Dist: odoo10-addon-sale-commission
